tamilstring/__init__.py
tamilstring/constant.py
tamilstring/helper.py
tamilstring/math.py
tamilstring/utf8.py
tamilstring-2.1.2626.dist-info/licenses/LICENCE
tamilstring-2.1.2626.dist-info/METADATA
tamilstring-2.1.2626.dist-info/WHEEL
tamilstring-2.1.2626.dist-info/top_level.txt
tamilstring-2.1.2626.dist-info/RECORD
