Metadata-Version: 2.4
Name: tamilstring
Version: 2.1.2626
Summary: tamilstring helps to handle tamil unicode characters lot more easier
Home-page: https://gitlab.com/boopalan-dev/tamilstring
Author: boopalan
Author-email: contact.boopalan@gmail.com
License: MIT
Classifier: Programming Language :: Python :: 3
Classifier: Operating System :: OS Independent
Requires-Python: >=3.6
License-File: LICENCE
Dynamic: author
Dynamic: author-email
Dynamic: classifier
Dynamic: description
Dynamic: description-content-type
Dynamic: home-page
Dynamic: license
Dynamic: license-file
Dynamic: requires-python
Dynamic: summary
